PracticeQuestions/CodeCrafters/EXP2_BitBalancer/Design/design.v
module bitbalancer(
    input wire clk,             //Input for clock(positive/negative)
    input wire reset,             //Input for reset(count resets to zero if rst = 1)
    input wire [7:0] in,      //Input for data vector of size 8-bits
    output reg [3:0] count    //Output register to store the count of ones in the given data
);
//function to count the ones of a 8-bit data - Combinational
function [3:0] count_ones;
    input [7:0] val;
    integer i;
    begin
        count_ones = 4'd0;
        for (i = 0; i < 8; i = i + 1) begin
            count_ones = count_ones + val[i];
        end
    end
endfunction
//main to count the number of ones for every new data
always @(posedge clk) begin
    if (reset) begin
        count <= 4'd0;
    end
    else begin
        count <= count_ones(in);
    end
end
endmodule

PracticeQuestions/CodeCrafters/EXP2_BitBalancer/TB/tb_bitbalancer.v
`timescale 1ns/1ps
module tb_bitbalancer;

    // Inputs
    reg clk;
    reg reset;
    reg [7:0] in;

    // Output
    wire [3:0] count;

    // Instantiate the DUT
    bitbalancer uut (
        .clk(clk),
        .reset(reset),
        .in(in),
        .count(count)
    );

    // Clock generation: 10ns period
    always #5 clk = ~clk;

    // Task to apply test vectors
    task apply_test(input [7:0] val, input [3:0] expected);
        begin
            in = val;
            @(posedge clk);
            #1;
            if (count !== expected)
                $display("Test failed for input %b: Expected = %0d, Got = %0d", val, expected, count);
            else
                $display("Test passed for input %b: Count = %0d", val, count);
        end
    endtask

    initial begin
        // VCD dump for waveform viewing
        $dumpfile("bitbalancer.vcd");
        $dumpvars(0, tb_bitbalancer);

        // Live monitor
        $monitor("Time=%0t | reset=%b | in=%b | count=%0d", $time, reset, in, count);

        // Initialization
        clk = 0;
        reset = 1;
        in = 8'd0;

        // Reset the DUT
        @(posedge clk);
        #1;
        reset = 0;

        // Apply test vectors (17 cases)
        apply_test(8'b0000_0000, 4'd0);  // All 0s
        apply_test(8'b1111_1111, 4'd8);  // All 1s
        apply_test(8'b0000_0001, 4'd1);  // LSB only
        apply_test(8'b1000_0000, 4'd1);  // MSB only
        apply_test(8'b1010_1010, 4'd4);  // Alternating 1s
        apply_test(8'b0101_0101, 4'd4);  // Reverse alternating
        apply_test(8'b0011_1100, 4'd4);  // Middle cluster
        apply_test(8'b0001_1000, 4'd2);  // Sparse middle
        apply_test(8'b0000_1111, 4'd4);  // Lower nibble
        apply_test(8'b1111_0000, 4'd4);  // Upper nibble
        apply_test(8'b1100_0011, 4'd4);  // Symmetric ends
        apply_test(8'b1001_0110, 4'd4);  // Mixed pattern
        apply_test(8'b0111_1110, 4'd6);  // Dense middle
        apply_test(8'b0000_0010, 4'd1);  // Middle bit
        apply_test(8'b0100_0001, 4'd2);  // Edge bits
        apply_test(8'b0010_0100, 4'd2);  // Center bits
        apply_test(8'b0110_0110, 4'd4);  // Balanced pattern

        // Test reset behavior
        reset = 1;
        @(posedge clk);
        #1;
        if (count !== 4'd0)
            $display("Reset test failed: Expected = 0, Got = %0d", count);
        else
            $display("Reset test passed: Count = %0d", count);

        $display("All tests completed.");
        $finish;
    end
endmodule

PracticeQuestions/CodeCrafters/EXP2_BitBalancer/bitbalancer.vcd
$date
	Tue Sep  2 15:41:26 2025
$end
$version
	Icarus Verilog
$end
$timescale
	1ps
$end
$scope module tb_bitbalancer $end
$var wire 4 ! count [3:0] $end
$var reg 1 " clk $end
$var reg 8 # in [7:0] $end
$var reg 1 $ reset $end
$scope module uut $end
$var wire 1 " clk $end
$var wire 8 % in [7:0] $end
$var wire 1 $ reset $end
$var reg 4 & count [3:0] $end
$scope function count_ones $end
$var reg 8 ' val [7:0] $end
$var integer 32 ( i [31:0] $end
$upscope $end
$upscope $end
$scope task apply_test $end
$var reg 4 ) expected [3:0] $end
$var reg 8 * val [7:0] $end
$upscope $end
$upscope $end
$enddefinitions $end
#0
$dumpvars
bx *
bx )
bx (
bx '
bx &
b0 %
1$
b0 #
0"
bx !
$end
#5000
b0 !
b0 &
1"
#6000
b0 )
b0 *
0$
#10000
0"
#15000
b1000 (
b0 '
1"
#16000
b11111111 #
b11111111 %
b1000 )
b11111111 *
#20000
0"
#25000
b1000 !
b1000 &
b1000 (
b11111111 '
1"
#26000
b1 #
b1 %
b1 )
b1 *
#30000
0"
#35000
b1 !
b1 &
b1000 (
b1 '
1"
#36000
b10000000 #
b10000000 %
b10000000 *
#40000
0"
#45000
b1000 (
b10000000 '
1"
#46000
b10101010 #
b10101010 %
b100 )
b10101010 *
#50000
0"
#55000
b100 !
b100 &
b1000 (
b10101010 '
1"
#56000
b1010101 #
b1010101 %
b1010101 *
#60000
0"
#65000
b1000 (
b1010101 '
1"
#66000
b111100 #
b111100 %
b111100 *
#70000
0"
#75000
b1000 (
b111100 '
1"
#76000
b11000 #
b11000 %
b10 )
b11000 *
#80000
0"
#85000
b10 !
b10 &
b1000 (
b11000 '
1"
#86000
b1111 #
b1111 %
b100 )
b1111 *
#90000
0"
#95000
b100 !
b100 &
b1000 (
b1111 '
1"
#96000
b11110000 #
b11110000 %
b11110000 *
#100000
0"
#105000
b1000 (
b11110000 '
1"
#106000
b11000011 #
b11000011 %
b11000011 *
#110000
0"
#115000
b1000 (
b11000011 '
1"
#116000
b10010110 #
b10010110 %
b10010110 *
#120000
0"
#125000
b1000 (
b10010110 '
1"
#126000
b1111110 #
b1111110 %
b110 )
b1111110 *
#130000
0"
#135000
b110 !
b110 &
b1000 (
b1111110 '
1"
#136000
b10 #
b10 %
b1 )
b10 *
#140000
0"
#145000
b1 !
b1 &
b1000 (
b10 '
1"
#146000
b1000001 #
b1000001 %
b10 )
b1000001 *
#150000
0"
#155000
b10 !
b10 &
b1000 (
b1000001 '
1"
#156000
b100100 #
b100100 %
b100100 *
#160000
0"
#165000
b1000 (
b100100 '
1"
#166000
b1100110 #
b1100110 %
b100 )
b1100110 *
#170000
0"
#175000
b100 !
b100 &
b1000 (
b1100110 '
1"
#176000
1$
#180000
0"
#185000
b0 !
b0 &
1"
