PracticeQuestions/CodeCrafters/EXP1_PulseTracer/Design/design.v
`timescale 1ns / 1ps

module PulseTracer #(
    parameter FILTER_LEN = 3
)(
    input  wire clk,
    input  wire rst_n,
    input  wire noisy_in,
    output reg  pulse_out
);

    reg [3:0] counter;   // counts stable highs

    always @(posedge clk or negedge rst_n) begin
        if(!rst_n) begin
            counter   <= 0;
            pulse_out <= 0;
        end
        else begin
            if(noisy_in) begin
                // increment counter until FILTER_LEN
                if(counter < FILTER_LEN)
                    counter <= counter + 1;

                // generate pulse exactly once when threshold is hit
                if(counter == FILTER_LEN - 1)
                    pulse_out <= 1;
                else
                    pulse_out <= 0;
            end
            else begin
                // reset when input goes low
                counter   <= 0;
                pulse_out <= 0;
            end
        end
    end

endmodule

PracticeQuestions/CodeCrafters/EXP1_PulseTracer/TB/tb_PulseTracer.v
`timescale 1ns / 1ps

module tb_PulseTracer;

    // Parameters
    parameter FILTER_LEN = 3;
    parameter CLK_PERIOD = 10;

    // Signals
    reg clk;
    reg rst_n;
    reg noisy_in;
    wire pulse_out;

    // Instantiate DUT
    PulseTracer #(.FILTER_LEN(FILTER_LEN)) dut (
        .clk(clk),
        .rst_n(rst_n),
        .noisy_in(noisy_in),
        .pulse_out(pulse_out)
    );

    // Clock generation
    initial clk = 0;
    always #(CLK_PERIOD/2) clk = ~clk;

    // Monitor
    always @(posedge clk)
        $display("Time %0t | noisy_in=%b | pulse_out=%b", $time, noisy_in, pulse_out);

    // Stimulus
    initial begin
        $dumpfile("pulse_tracer_full.vcd");
        $dumpvars(0, tb_PulseTracer);

        // Reset
        rst_n = 0;
        noisy_in = 0;
        #(2*CLK_PERIOD);
        rst_n = 1;

        // -------------------------------
        // TESTCASE 1: Glitch < FILTER_LEN
        // -------------------------------
        $display("\n[TC1] Short Glitch (Should NOT trigger pulse)");
        noisy_in = 1; #(1*CLK_PERIOD);
        noisy_in = 0; #(5*CLK_PERIOD);

        // -------------------------------
        // TESTCASE 2: Valid pulse
        // -------------------------------
        $display("\n[TC2] Stable high for FILTER_LEN (Should trigger 1 pulse)");
        noisy_in = 1; #(FILTER_LEN * CLK_PERIOD);
        noisy_in = 1; #(CLK_PERIOD);  // Pulse expected here
        noisy_in = 0; #(3 * CLK_PERIOD);

        // -------------------------------
        // TESTCASE 3: Noise — alternating glitches
        // -------------------------------
        $display("\n[TC3] Alternating glitches (Should NOT trigger pulse)");
        repeat (10) begin
            noisy_in = $random % 2;
            #(CLK_PERIOD);
        end

        // -------------------------------
        // TESTCASE 4: Back-to-back valid pulses
        // -------------------------------
        $display("\n[TC4] Two valid pulses with low separation");
        noisy_in = 1; #(FILTER_LEN * CLK_PERIOD);
        noisy_in = 1; #(CLK_PERIOD);  // Pulse 1
        noisy_in = 0; #(3 * CLK_PERIOD);
        noisy_in = 1; #(FILTER_LEN * CLK_PERIOD);
        noisy_in = 1; #(CLK_PERIOD);  // Pulse 2
        noisy_in = 0; #(3 * CLK_PERIOD);

        // -------------------------------
        // TESTCASE 5: Long hold high (No multiple pulses)
        // -------------------------------
        $display("\n[TC5] Long held high (Only one pulse)");
        noisy_in = 1; #(FILTER_LEN * CLK_PERIOD);
        noisy_in = 1; #(10 * CLK_PERIOD); // Should only see 1 pulse
        noisy_in = 0; #(3 * CLK_PERIOD);

        // -------------------------------
        // TESTCASE 6: Glitch during rising period
        // -------------------------------
        $display("\n[TC6] Glitch during FILTER_LEN build-up");
        noisy_in = 1; #(1 * CLK_PERIOD);
        noisy_in = 0; #(1 * CLK_PERIOD);  // breaks the streak
        noisy_in = 1; #(FILTER_LEN * CLK_PERIOD);
        noisy_in = 1; #(CLK_PERIOD);      // Pulse expected here
        noisy_in = 0; #(3 * CLK_PERIOD);

        // -------------------------------
        // TESTCASE 7: Random noise + controlled pulses
        // -------------------------------
        $display("\n[TC7] Random noise, then forced valid pulse");
        repeat (20) begin
            noisy_in = $random % 2;
            #(CLK_PERIOD);
        end
        noisy_in = 0; #(3 * CLK_PERIOD);  // reset
        noisy_in = 1; #(FILTER_LEN * CLK_PERIOD);
        noisy_in = 1; #(CLK_PERIOD);      // Pulse expected here
        noisy_in = 0; #(3 * CLK_PERIOD);

        // Done
        $display("\nAll tests complete.");
        $finish;
    end

endmodule

PracticeQuestions/CodeCrafters/EXP1_PulseTracer/pulse_tracer_full.vcd
$date
	Sat Sep  6 12:25:12 2025
$end
$version
	Icarus Verilog
$end
$timescale
	1ps
$end
$scope module tb_PulseTracer $end
$var wire 1 ! pulse_out $end
$var reg 1 " clk $end
$var reg 1 # noisy_in $end
$var reg 1 $ rst_n $end
$scope module dut $end
$var wire 1 " clk $end
$var wire 1 # noisy_in $end
$var wire 1 $ rst_n $end
$var reg 4 % counter [3:0] $end
$var reg 1 ! pulse_out $end
$upscope $end
$upscope $end
$enddefinitions $end
#0
$dumpvars
b0 %
0$
0#
0"
0!
$end
#5000
1"
#10000
0"
#15000
1"
#20000
0"
1#
1$
#25000
b1 %
1"
#30000
0"
0#
#35000
b0 %
1"
#40000
0"
#45000
1"
#50000
0"
#55000
1"
#60000
0"
#65000
1"
#70000
0"
#75000
1"
#80000
0"
1#
#85000
b1 %
1"
#90000
0"
#95000
b10 %
1"
#100000
0"
#105000
1!
b11 %
1"
#110000
0"
#115000
0!
1"
#120000
0"
0#
#125000
b0 %
1"
#130000
0"
#135000
1"
#140000
0"
#145000
1"
#150000
0"
#155000
1"
#160000
0"
1#
#165000
b1 %
1"
#170000
0"
#175000
b10 %
1"
#180000
0"
#185000
1!
b11 %
1"
#190000
0"
#195000
0!
1"
#200000
0"
#205000
1"
#210000
0"
#215000
1"
#220000
0"
0#
#225000
b0 %
1"
#230000
0"
1#
#235000
b1 %
1"
#240000
0"
#245000
b10 %
1"
#250000
0"
#255000
1!
b11 %
1"
#260000
0"
#265000
0!
1"
#270000
0"
#275000
1"
#280000
0"
#285000
1"
#290000
0"
0#
#295000
b0 %
1"
#300000
0"
#305000
1"
#310000
0"
#315000
1"
#320000
0"
1#
#325000
b1 %
1"
#330000
0"
#335000
b10 %
1"
#340000
0"
#345000
1!
b11 %
1"
#350000
0"
#355000
0!
1"
#360000
0"
0#
#365000
b0 %
1"
#370000
0"
#375000
1"
#380000
0"
#385000
1"
#390000
0"
1#
#395000
b1 %
1"
#400000
0"
#405000
b10 %
1"
#410000
0"
#415000
1!
b11 %
1"
#420000
0"
#425000
0!
1"
#430000
0"
#435000
1"
#440000
0"
#445000
1"
#450000
0"
#455000
1"
#460000
0"
#465000
1"
#470000
0"
#475000
1"
#480000
0"
#485000
1"
#490000
0"
#495000
1"
#500000
0"
#505000
1"
#510000
0"
#515000
1"
#520000
0"
0#
#525000
b0 %
1"
#530000
0"
#535000
1"
#540000
0"
#545000
1"
#550000
0"
1#
#555000
b1 %
1"
#560000
0"
0#
#565000
b0 %
1"
#570000
0"
1#
#575000
b1 %
1"
#580000
0"
#585000
b10 %
1"
#590000
0"
#595000
1!
b11 %
1"
#600000
0"
#605000
0!
1"
#610000
0"
0#
#615000
b0 %
1"
#620000
0"
#625000
1"
#630000
0"
#635000
1"
#640000
0"
#645000
1"
#650000
0"
1#
#655000
b1 %
1"
#660000
0"
#665000
b10 %
1"
#670000
0"
0#
#675000
b0 %
1"
#680000
0"
1#
#685000
b1 %
1"
#690000
0"
0#
#695000
b0 %
1"
#700000
0"
1#
#705000
b1 %
1"
#710000
0"
0#
#715000
b0 %
1"
#720000
0"
1#
#725000
b1 %
1"
#730000
0"
#735000
b10 %
1"
#740000
0"
0#
#745000
b0 %
1"
#750000
0"
1#
#755000
b1 %
1"
#760000
0"
0#
#765000
b0 %
1"
#770000
0"
#775000
1"
#780000
0"
#785000
1"
#790000
0"
1#
#795000
b1 %
1"
#800000
0"
0#
#805000
b0 %
1"
#810000
0"
1#
#815000
b1 %
1"
#820000
0"
#825000
b10 %
1"
#830000
0"
#835000
1!
b11 %
1"
#840000
0"
0#
#845000
0!
b0 %
1"
#850000
0"
#855000
1"
#860000
0"
#865000
1"
#870000
0"
1#
#875000
b1 %
1"
#880000
0"
#885000
b10 %
1"
#890000
0"
#895000
1!
b11 %
1"
#900000
0"
#905000
0!
1"
#910000
0"
0#
#915000
b0 %
1"
