PracticeQuestions/CodeCrafters/EXP3_NibbleSwapper/Design/design.v
module nibbleswapper(
    input clk,
    input reset,
    input [7:0]in,
    input swap_en,
    output reg [7:0]out
);
always @(posedge clk) begin
    if (reset) begin
        out <= 8'h00;
    end
    else if (swap_en) begin
        out <= {in[3:0],in[7:4]};
    end
end
endmodule

PracticeQuestions/CodeCrafters/EXP3_NibbleSwapper/TB/tb_nibbleswap.v
module tb_nibbleswapper;

    // DUT signals
    reg clk;
    reg reset;
    reg [7:0] in;
    reg swap_en;
    wire [7:0] out;

    // Instantiate DUT
    nibbleswapper dut (
        .clk(clk),
        .reset(reset),
        .in(in),
        .swap_en(swap_en),
        .out(out)
    );

    // Clock generation
    always #5 clk = ~clk;

    // Helper: expected swap
    function [7:0] expected_swap(input [7:0] x);
        expected_swap = {x[3:0], x[7:4]};
    endfunction

    // Apply stimulus
    task apply_swap(input [7:0] val, input enable, input [7:0] expected);
        begin
            in = val;
            swap_en = enable;
            @(posedge clk); #1;

            if (out !== expected)
                $display(" FAIL: in=%h swap_en=%b → out=%h (Expected: %h)", val, enable, out, expected);
            else
                $display("PASS: in=%h swap_en=%b → out=%h", val, enable, out);
        end
    endtask

    initial begin
        $dumpfile("nibbleswapper.vcd");
        $dumpvars(0, tb_nibbleswapper);

        $display("=== Starting NibbleSwapper Test ===");

        clk = 0; reset = 1; in = 8'h00; swap_en = 0;
        #12; reset = 0;

        // === Critical Testcases ===
        $display("--- Critical Testcases ---");

        // 1. Reset behavior
        if (out !== 8'h00) $display(" FAIL: Reset output not 0");

        // 2. Normal swap: 0x71 → 0x17
        apply_swap(8'h71, 1, 8'h17);

        // 3. Hold output when swap_en = 0
        apply_swap(8'hA5, 0, 8'h17); // No change expected

        // 4. Swap again: 0xB4 → 0x4B
        apply_swap(8'hB4, 1, 8'h4B);

        // 5. swap_en toggling
        apply_swap(8'hC3, 1, 8'h3C);
        apply_swap(8'hF0, 0, 8'h3C); // Should hold
        apply_swap(8'hF0, 1, 8'h0F); // Swap now

        // 6. Back-to-back swaps
        apply_swap(8'h11, 1, 8'h11);
        apply_swap(8'h22, 1, 8'h22);

        // 7. Same input twice, validate repeated swap
        apply_swap(8'h3C, 1, 8'hC3);
        apply_swap(8'h3C, 1, 8'hC3);

        // 8. Edge: 0x00 → should stay 0
        apply_swap(8'h00, 1, 8'h00);

        // 9. Edge: 0xFF → swap remains 0xFF
        apply_swap(8'hFF, 1, 8'hFF);

        // 10. Glitch check: swap_en = 0 on active clock → output should hold
        in = 8'h9A;
        swap_en = 0;
        @(posedge clk); #1;
        if (out !== 8'hFF) // last was FF
            $display("FAIL: Output changed unexpectedly on swap_en=0");
        else
            $display(" PASS: Output held on swap_en=0");

        // ===  Generic Testcases ===
        $display("--- Generic Testcases ---");

        apply_swap(8'hA5, 1, expected_swap(8'hA5));
        apply_swap(8'h5A, 1, expected_swap(8'h5A));
        apply_swap(8'h0F, 1, expected_swap(8'h0F));
        apply_swap(8'hF0, 1, expected_swap(8'hF0));
        apply_swap(8'hAA, 1, expected_swap(8'hAA));
        apply_swap(8'h55, 1, expected_swap(8'h55));
        apply_swap(8'hC0, 1, expected_swap(8'hC0));
        apply_swap(8'h03, 1, expected_swap(8'h03));
        apply_swap(8'h10, 1, expected_swap(8'h10));
        apply_swap(8'h01, 1, expected_swap(8'h01));

        $display("=== NibbleSwapper Test Completed ===");
        $finish;
    end

endmodule

PracticeQuestions/CodeCrafters/EXP3_NibbleSwapper/Sim/nibbleswapper.vcd
$date
	Thu Sep  4 20:49:24 2025
$end
$version
	Icarus Verilog
$end
$timescale
	1s
$end
$scope module tb_nibbleswapper $end
$var wire 8 ! out [7:0] $end
$var reg 1 " clk $end
$var reg 8 # in [7:0] $end
$var reg 1 $ reset $end
$var reg 1 % swap_en $end
$scope function expected_swap $end
$var reg 8 & x [7:0] $end
$upscope $end
$scope module dut $end
$var wire 1 " clk $end
$var wire 8 ' in [7:0] $end
$var wire 1 $ reset $end
$var wire 1 % swap_en $end
$var reg 8 ( out [7:0] $end
$upscope $end
$scope task apply_swap $end
$var reg 1 ) enable $end
$var reg 8 * expected [7:0] $end
$var reg 8 + val [7:0] $end
$upscope $end
$upscope $end
$enddefinitions $end
#0
$dumpvars
bx +
bx *
x)
bx (
b0 '
bx &
0%
1$
b0 #
0"
bx !
$end
#5
b0 !
b0 (
1"
#10
0"
#12
1%
b1110001 #
b1110001 '
b10111 *
1)
b1110001 +
0$
#15
b10111 !
b10111 (
1"
#16
0%
b10100101 #
b10100101 '
0)
b10100101 +
#20
0"
#25
1"
#26
1%
b10110100 #
b10110100 '
b1001011 *
1)
b10110100 +
#30
0"
#35
b1001011 !
b1001011 (
1"
#36
b11000011 #
b11000011 '
b111100 *
b11000011 +
#40
0"
#45
b111100 !
b111100 (
1"
#46
0%
b11110000 #
b11110000 '
0)
b11110000 +
#50
0"
#55
1"
#56
1%
b1111 *
1)
#60
0"
#65
b1111 !
b1111 (
1"
#66
b10001 #
b10001 '
b10001 *
b10001 +
#70
0"
#75
b10001 !
b10001 (
1"
#76
b100010 #
b100010 '
b100010 *
b100010 +
#80
0"
#85
b100010 !
b100010 (
1"
#86
b111100 #
b111100 '
b11000011 *
b111100 +
#90
0"
#95
b11000011 !
b11000011 (
1"
#100
0"
#105
1"
#106
b0 #
b0 '
b0 *
b0 +
#110
0"
#115
b0 !
b0 (
1"
#116
b11111111 #
b11111111 '
b11111111 *
b11111111 +
#120
0"
#125
b11111111 !
b11111111 (
1"
#126
0%
b10011010 #
b10011010 '
#130
0"
#135
1"
#136
1%
b10100101 #
b10100101 '
b1011010 *
b10100101 &
b10100101 +
#140
0"
#145
b1011010 !
b1011010 (
1"
#146
b1011010 #
b1011010 '
b10100101 *
b1011010 &
b1011010 +
#150
0"
#155
b10100101 !
b10100101 (
1"
#156
b1111 #
b1111 '
b11110000 *
b1111 &
b1111 +
#160
0"
#165
b11110000 !
b11110000 (
1"
#166
b11110000 #
b11110000 '
b1111 *
b11110000 &
b11110000 +
#170
0"
#175
b1111 !
b1111 (
1"
#176
b10101010 #
b10101010 '
b10101010 *
b10101010 &
b10101010 +
#180
0"
#185
b10101010 !
b10101010 (
1"
#186
b1010101 #
b1010101 '
b1010101 *
b1010101 &
b1010101 +
#190
0"
#195
b1010101 !
b1010101 (
1"
#196
b11000000 #
b11000000 '
b1100 *
b11000000 &
b11000000 +
#200
0"
#205
b1100 !
b1100 (
1"
#206
b11 #
b11 '
b110000 *
b11 &
b11 +
#210
0"
#215
b110000 !
b110000 (
1"
#216
b10000 #
b10000 '
b1 *
b10000 &
b10000 +
#220
0"
#225
b1 !
b1 (
1"
#226
b1 #
b1 '
b10000 *
b1 &
b1 +
#230
0"
#235
b10000 !
b10000 (
1"
