PracticeQuestions/CodeCrafters/EXP4_EvenOddFSM/Design/design.v
module evenoddfsm(
    input wire clk,
    input wire reset,
    input wire in_valid,
    input wire [7:0] data_in,
    output reg even,
    output reg odd
);
    parameter EVEN_STATE = 1'b0;
    parameter ODD_STATE = 1'b1;
reg state,next_state;
always @(posedge clk or posedge reset) begin
    if(reset) begin
        state <= EVEN_STATE;
    end
    else begin
        state <= next_state;
    end
end
always @(*) begin
    next_state = state;
    if(in_valid) begin
        if(data_in[0] == 1'b0) begin
            next_state = EVEN_STATE;
        end
        else begin
            next_state = ODD_STATE;
        end
    end
end
always @(*) begin
    even = (state == EVEN_STATE);
    odd = (state == ODD_STATE);
end
endmodule

PracticeQuestions/CodeCrafters/EXP4_EvenOddFSM/TB/tb_evenoddfsm.v
`timescale 1ns / 1ps

module tb_evenoddfsm;

    // Inputs
    reg clk;
    reg reset;
    reg in_valid;
    reg [7:0] data_in;

    // Outputs
    wire even;
    wire odd;

    // Instantiate the DUT
    evenoddfsm dut (
        .clk(clk),
        .reset(reset),
        .in_valid(in_valid),
        .data_in(data_in),
        .even(even),
        .odd(odd)
    );

    // Clock Generation: 10ns period
    initial clk = 0;
    always #5 clk = ~clk;

    // Task to apply a single input vector
    task apply_input(
        input [7:0] din, 
        input valid, 
        input [1:0] expected  // 2'b01 for even, 2'b10 for odd
    );
        begin
            @(negedge clk);
            in_valid = valid;
            data_in = din;
            @(posedge clk);
            #1;

            $display("[Time %0t] Input: %3d | in_valid: %b | EVEN: %b | ODD: %b | Expected: %s",
                $time, din, valid, even, odd,
                (expected == 2'b01) ? "EVEN" :
                (expected == 2'b10) ? "ODD" : "NO CHANGE");

            if (valid) begin
                if ((expected == 2'b01 && even !== 1'b1) || 
                    (expected == 2'b10 && odd !== 1'b1)) begin
                    $display("FAILED: Input %d | Expected: %b | Got EVEN: %b, ODD: %b", 
                        din, expected, even, odd);
                end else begin
                    $display("PASSED");
                end
            end
        end
    endtask

    // Test Procedure
    initial begin
        // VCD dump
        $dumpfile("evenoddfsm.vcd");
        $dumpvars(0, tb_evenoddfsm);

        // Initial values
        clk = 0;
        reset = 1;
        in_valid = 0;
        data_in = 0;

        // Apply Reset
        #12 reset = 0;

        // -------------------------------
        //  Critical Test Cases
        // -------------------------------
        apply_input(8'd0,    1, 2'b01); // even
        apply_input(8'd1,    1, 2'b10); // odd
        apply_input(8'd2,    1, 2'b01); // even
        apply_input(8'd255,  1, 2'b10); // odd (max value)
        apply_input(8'd128,  1, 2'b01); // even (MSB = 1)
        apply_input(8'd127,  1, 2'b10); // odd
        apply_input(8'd254,  1, 2'b01); // even
        apply_input(8'd3,    0, 2'b00); // in_valid = 0 → hold state
        apply_input(8'd4,    1, 2'b01); // even
        apply_input(8'd5,    1, 2'b10); // odd

        // -------------------------------
        // Generic Test Cases
        // -------------------------------
        apply_input(8'd10,   1, 2'b01);
        apply_input(8'd11,   1, 2'b10);
        apply_input(8'd6,    0, 2'b00); // in_valid = 0 → no change
        apply_input(8'd6,    1, 2'b01);
        apply_input(8'd9,    1, 2'b10);
        apply_input(8'd12,   1, 2'b01);
        apply_input(8'd13,   1, 2'b10);
        apply_input(8'd14,   1, 2'b01);
        apply_input(8'd15,   1, 2'b10);
        apply_input(8'd16,   1, 2'b01);

        $display("All test cases executed.");
        #20 $finish;
    end

endmodule

PracticeQuestions/CodeCrafters/EXP4_EvenOddFSM/Sim/evenoddfsm.vcd
$date
	Sat Sep  6 15:53:48 2025
$end
$version
	Icarus Verilog
$end
$timescale
	1ps
$end
$scope module tb_evenoddfsm $end
$var wire 1 ! odd $end
$var wire 1 " even $end
$var reg 1 # clk $end
$var reg 8 $ data_in [7:0] $end
$var reg 1 % in_valid $end
$var reg 1 & reset $end
$scope module dut $end
$var wire 1 # clk $end
$var wire 8 ' data_in [7:0] $end
$var wire 1 % in_valid $end
$var wire 1 & reset $end
$var reg 1 " even $end
$var reg 1 ( next_state $end
$var reg 1 ! odd $end
$var reg 1 ) state $end
$upscope $end
$scope task apply_input $end
$var reg 8 * din [7:0] $end
$var reg 2 + expected [1:0] $end
$var reg 1 , valid $end
$upscope $end
$upscope $end
$enddefinitions $end
#0
$dumpvars
x,
bx +
bx *
0)
0(
b0 '
1&
0%
b0 $
0#
1"
0!
$end
#5000
1#
#10000
0#
#12000
b1 +
1,
b0 *
0&
#15000
1#
#20000
1%
0#
#25000
1#
#26000
b10 +
b1 *
#30000
1(
b1 $
b1 '
0#
#35000
1!
0"
1)
1#
#36000
b1 +
b10 *
#40000
0(
b10 $
b10 '
0#
#45000
0!
1"
0)
1#
#46000
b10 +
b11111111 *
#50000
1(
b11111111 $
b11111111 '
0#
#55000
1!
0"
1)
1#
#56000
b1 +
b10000000 *
#60000
0(
b10000000 $
b10000000 '
0#
#65000
0!
1"
0)
1#
#66000
b10 +
b1111111 *
#70000
1(
b1111111 $
b1111111 '
0#
#75000
1!
0"
1)
1#
#76000
b1 +
b11111110 *
#80000
0(
b11111110 $
b11111110 '
0#
#85000
0!
1"
0)
1#
#86000
b0 +
0,
b11 *
#90000
b11 $
b11 '
0%
0#
#95000
1#
#96000
b1 +
1,
b100 *
#100000
b100 $
b100 '
1%
0#
#105000
1#
#106000
b10 +
b101 *
#110000
1(
b101 $
b101 '
0#
#115000
1!
0"
1)
1#
#116000
b1 +
b1010 *
#120000
0(
b1010 $
b1010 '
0#
#125000
0!
1"
0)
1#
#126000
b10 +
b1011 *
#130000
1(
b1011 $
b1011 '
0#
#135000
1!
0"
1)
1#
#136000
b0 +
0,
b110 *
#140000
b110 $
b110 '
0%
0#
#145000
1#
#146000
b1 +
1,
#150000
0(
1%
0#
#155000
0!
1"
0)
1#
#156000
b10 +
b1001 *
#160000
1(
b1001 $
b1001 '
0#
#165000
1!
0"
1)
1#
#166000
b1 +
b1100 *
#170000
0(
b1100 $
b1100 '
0#
#175000
0!
1"
0)
1#
#176000
b10 +
b1101 *
#180000
1(
b1101 $
b1101 '
0#
#185000
1!
0"
1)
1#
#186000
b1 +
b1110 *
#190000
0(
b1110 $
b1110 '
0#
#195000
0!
1"
0)
1#
#196000
b10 +
b1111 *
#200000
1(
b1111 $
b1111 '
0#
#205000
1!
0"
1)
1#
#206000
b1 +
b10000 *
#210000
0(
b10000 $
b10000 '
0#
#215000
0!
1"
0)
1#
